marise/__init__.py
marise/_modidx.py
marise/core.py
marise-0.0.1.dist-info/LICENSE
marise-0.0.1.dist-info/METADATA
marise-0.0.1.dist-info/WHEEL
marise-0.0.1.dist-info/entry_points.txt
marise-0.0.1.dist-info/top_level.txt
marise-0.0.1.dist-info/RECORD
